jupyter_map_gl/__init__.py
jupyter_map_gl/glmap.py
jupyter_map_gl-0.2.2.data/data/share/jupyter/nbextensions/jupyter_map_gl/index.js
jupyter_map_gl-0.2.2.dist-info/DESCRIPTION.rst
jupyter_map_gl-0.2.2.dist-info/METADATA
jupyter_map_gl-0.2.2.dist-info/RECORD
jupyter_map_gl-0.2.2.dist-info/WHEEL
jupyter_map_gl-0.2.2.dist-info/metadata.json
jupyter_map_gl-0.2.2.dist-info/top_level.txt
