Metadata-Version: 2.0
Name: jupyter-map-gl
Version: 0.2.2
Summary: A wrapper around react-map-gl components for use in jupyter notebooks
Home-page: https://bitbucket.com/timbr-io/jupyter-map-gl
Author: Chris Helm
Author-email: chelm@timbr.io
License: MIT
Platform: UNKNOWN
Requires-Dist: ipython
Requires-Dist: jupyter-react
